osensapy/__init__.py
osensapy/minimalmodbusosensa.py
osensapy/osensapy.py
osensapy/osensapy_example.py
osensapy-0.1.7.dist-info/LICENSE-3RD-PARTY.txt
osensapy-0.1.7.dist-info/LICENSE.txt
osensapy-0.1.7.dist-info/METADATA
osensapy-0.1.7.dist-info/WHEEL
osensapy-0.1.7.dist-info/top_level.txt
osensapy-0.1.7.dist-info/RECORD
