Metadata-Version: 2.1
Name: osensapy
Version: 0.1.7
Summary: OSENSA Python library
Home-page: UNKNOWN
Author: OSENSA Innovations
Author-email: cng@osensa.com
License: MIT
Platform: UNKNOWN
Requires-Python: >=2.6
Requires-Dist: numpy
Requires-Dist: pyserial
